confusion_matrix/__init__.py
confusion_matrix/version.py
confusion_matrix_sebastian_achim_mueller-0.0.5.dist-info/LICENSE
confusion_matrix_sebastian_achim_mueller-0.0.5.dist-info/METADATA
confusion_matrix_sebastian_achim_mueller-0.0.5.dist-info/WHEEL
confusion_matrix_sebastian_achim_mueller-0.0.5.dist-info/top_level.txt
confusion_matrix_sebastian_achim_mueller-0.0.5.dist-info/RECORD
