Metadata-Version: 2.1
Name: confusion-matrix-sebastian-achim-mueller
Version: 0.0.5
Summary: Create confusion-matrices
Home-page: https://github.com/cherenkov-plenoscope/confusion_matrix
Author: Sebastian Achim Mueller
Author-email: sebastian-achim.mueller@mpi-hd.mpg.de
Classifier: Programming Language :: Python :: 3
Classifier: License :: OSI Approved :: MIT License
Classifier: Operating System :: OS Independent
Classifier: Natural Language :: English
Classifier: Intended Audience :: Science/Research
License-File: LICENSE
